{
  "citation": "",
  "description": "",
  "features": {
    "Customer": {
      "dtype": "string",
      "_type": "Value"
    },
    "Type": {
      "dtype": "string",
      "_type": "Value"
    },
    "Text": {
      "dtype": "string",
      "_type": "Value"
    },
    "Summary": {
      "dtype": "string",
      "_type": "Value"
    },
    "sim_score": {
      "dtype": "float64",
      "_type": "Value"
    },
    "split": {
      "dtype": "string",
      "_type": "Value"
    }
  },
  "homepage": "",
  "license": ""
}